LICENSE
MANIFEST.in
README.rst
setup.cfg
setup.py
django_biz_flow/__init__.py
django_biz_flow.egg-info/PKG-INFO
django_biz_flow.egg-info/SOURCES.txt
django_biz_flow.egg-info/dependency_links.txt
django_biz_flow.egg-info/requires.txt
django_biz_flow.egg-info/top_level.txt
django_biz_flow/onboarding/__init__.py
django_biz_flow/onboarding/admin.py
django_biz_flow/onboarding/apps.py
django_biz_flow/onboarding/models.py
django_biz_flow/onboarding/serializer.py
django_biz_flow/onboarding/tests.py
django_biz_flow/onboarding/urls.py
django_biz_flow/onboarding/migrations/0001_initial.py
django_biz_flow/onboarding/migrations/0002_personaldetails_businessprofile_and_more.py
django_biz_flow/onboarding/migrations/0003_personaldetails_user.py
django_biz_flow/onboarding/migrations/0004_alter_personaldetails_user.py
django_biz_flow/onboarding/migrations/__init__.py